CHANGELOG.txt
LICENCE.txt
MANIFEST.in
README.md
requirements.txt
setup.py
test.py
searoute/__init__.py
searoute/searoute.py
searoute/utils.py
searoute.egg-info/PKG-INFO
searoute.egg-info/SOURCES.txt
searoute.egg-info/dependency_links.txt
searoute.egg-info/requires.txt
searoute.egg-info/top_level.txt
searoute/classes/__init__.py
searoute/classes/area_feature.py
searoute/classes/kdtree.py
searoute/classes/marnet.py
searoute/classes/passages.py
searoute/classes/ports.py
searoute/classes/ports_props.py
searoute/data/.DS_Store
searoute/data/__init__.py
searoute/data/marnet_dict.py
searoute/data/marnet_searoute.geojson
searoute/data/ports.geojson
searoute/data/ports_dict.py
searoute/data/segment.geojson
searoute/tests/__init__.py
searoute/tests/test_area_feature.py
searoute/tests/test_mandatory_passages.py
searoute/tests/test_ports.py
searoute/tests/test_searoute.py
searoute/tests/test_utils.py