Metadata-Version: 2.1
Name: searoute
Version: 1.4.3
Summary: A python package for generating the shortest sea route between two points on Earth.
Home-page: 
Author: Gent Halili
Author-email: genthalili@users.noreply.github.com
License: Apache License 2.0
Project-URL: Documentation, https://github.com/genthalili/searoute-py/blob/main/README.md
Project-URL: Source, https://github.com/genthalili/searoute-py
Keywords: searoute map sea route ocean ports
Classifier: Development Status :: 5 - Production/Stable
Classifier: Intended Audience :: Education
Classifier: Intended Audience :: Customer Service
Classifier: Intended Audience :: Developers
Classifier: Intended Audience :: Information Technology
Classifier: Intended Audience :: Science/Research
Classifier: Intended Audience :: Telecommunications Industry
Classifier: Operating System :: OS Independent
Classifier: License :: OSI Approved :: Apache Software License
Classifier: Programming Language :: Python :: 3
License-File: LICENCE.txt
Requires-Dist: geojson
Requires-Dist: networkx
